artec/__init__.py
artec/__main__.py
artec/argparser.py
artec/boiler.py
artec/exceptions.py
artec/repo.py
artec/templates.py
artec/temp/__init__.py
Artec-0.3.1.dist-info/LICENSE
Artec-0.3.1.dist-info/METADATA
Artec-0.3.1.dist-info/WHEEL
Artec-0.3.1.dist-info/entry_points.txt
Artec-0.3.1.dist-info/top_level.txt
Artec-0.3.1.dist-info/RECORD
