Metadata-Version: 2.1
Name: Artec
Version: 0.3.1
Summary: Creates a configurable python project template in a given directory.
Author-email: HushmKun <HushmKun@outlook.com>, Link- <bsm.dgdy@gmail.com>
License: GNU GENERAL PUBLIC LICENSE
Project-URL: Homepage, https://github.com/HushmKun/Artec
Project-URL: Bug Tracker, https://github.com/HushmKun/Artec/issues
Classifier: Intended Audience :: Developers
Classifier: Development Status :: 4 - Beta
Classifier: Environment :: Console
Classifier: Programming Language :: Python :: 3
Classifier: Topic :: Software Development :: Build Tools
Requires-Python: >=3.7
License-File: LICENSE
Requires-Dist: GitPython
Provides-Extra: dev
Requires-Dist: black ; extra == 'dev'
Requires-Dist: flake8 ; extra == 'dev'
Provides-Extra: test
Requires-Dist: pytest ; extra == 'test'
